photonforge/analytic_models.py
photonforge/circuit_base.py
photonforge/stencil.py
photonforge/extension.cpython-312-x86_64-linux-gnu.so
photonforge/utils.py
photonforge/sink_time_steppers.py
photonforge/plotting.py
photonforge/modulator_time_steppers.py
photonforge/eme_model.py
photonforge/thumbnails.py
photonforge/_schema.py
photonforge/parametric_utils.py
photonforge/typing.py
photonforge/s_matrix_time_stepper.py
photonforge/monte_carlo.py
photonforge/parametric.py
photonforge/analytic_time_steppers.py
photonforge/pretty.py
photonforge/data_model.py
photonforge/tidy3d_model.py
photonforge/cache.py
photonforge/netlist.py
photonforge/source_time_steppers.py
photonforge/__init__.py
photonforge/circuit_time_stepper.py
photonforge/circuit_model.py
photonforge/live_viewer.py
photonforge/static/icons/home.svg
photonforge/static/icons/ruler.svg
photonforge/static/icons/photonforge.svg
photonforge/static/icons/grid.svg
photonforge/static/icons/clear.svg
photonforge/static/css/styles.css
photonforge/static/js/main.js
photonforge/thumbnails/to_ps.svg
photonforge/thumbnails/black_box.svg
photonforge/thumbnails/termination.svg
photonforge/thumbnails/mrr.svg
photonforge/thumbnails/eo_ps.svg
photonforge/thumbnails/mmi1x2.svg
photonforge/thumbnails/mzm.svg
photonforge/thumbnails/mrm.svg
photonforge/thumbnails/psgc.svg
photonforge/thumbnails/photodiode.svg
photonforge/thumbnails/wg.svg
photonforge/thumbnails/s-bend.svg
photonforge/thumbnails/taper.svg
photonforge/thumbnails/laser.svg
photonforge/thumbnails/grating_coupler.svg
photonforge/thumbnails/cw_laser.svg
photonforge/thumbnails/edge_coupler.svg
photonforge/thumbnails/connection.svg
photonforge/thumbnails/dual_mrr.svg
photonforge/thumbnails/bondpad.svg
photonforge/thumbnails/wdm.svg
photonforge/thumbnails/source.svg
photonforge/thumbnails/u-bend.svg
photonforge/thumbnails/bend.svg
photonforge/thumbnails/electrical_termination.svg
photonforge-1.3.1.dist-info/WHEEL
photonforge-1.3.1.dist-info/entry_points.txt
photonforge-1.3.1.dist-info/METADATA
photonforge-1.3.1.dist-info/RECORD
photonforge-1.3.1.dist-info/licenses/LICENSE
